{
  "UserEvents": {
    "eb9b018caf07b51b0914ce96fcf317ab532a2d06983c4d374dfd66c5516f0933": [
      {
        "NewName": "MapEditor.ButtonConfirmInstance",
        "OldName": null,
        "ElementType": "Screens",
        "EventType": 5,
        "TimestampUtc": "2025-09-26T00:29:15.1057269Z"
      },
      {
        "NewName": "FeedbackPanel",
        "OldName": null,
        "ElementType": "Components",
        "EventType": 0,
        "TimestampUtc": "2025-09-26T00:34:18.2438941Z"
      },
      {
        "NewName": "FeedbackPanel (Container).ColoredRectangleInstance",
        "OldName": null,
        "ElementType": "Components",
        "EventType": 5,
        "TimestampUtc": "2025-09-26T00:34:32.1667183Z"
      },
      {
        "NewName": "FeedbackPanel (Container).TextInstance",
        "OldName": null,
        "ElementType": "Components",
        "EventType": 5,
        "TimestampUtc": "2025-09-26T00:36:06.8587603Z"
      },
      {
        "NewName": "FeedbackPanel (Container).SpriteInstance",
        "OldName": null,
        "ElementType": "Components",
        "EventType": 5,
        "TimestampUtc": "2025-09-26T00:38:14.706427Z"
      },
      {
        "NewName": "FeedbackPanel (Container).SpriteInstance1",
        "OldName": null,
        "ElementType": "Components",
        "EventType": 5,
        "TimestampUtc": "2025-09-26T00:39:05.9516375Z"
      },
      {
        "NewName": "FeedbackPanel (Container).SuccessIcon",
        "OldName": "FeedbackPanel (Container).SpriteInstance",
        "ElementType": "Components",
        "EventType": 7,
        "TimestampUtc": "2025-09-26T00:39:21.9732047Z"
      },
      {
        "NewName": "FeedbackPanel (Container).ErrorIcon",
        "OldName": "FeedbackPanel (Container).SuccessIcon",
        "ElementType": "Components",
        "EventType": 7,
        "TimestampUtc": "2025-09-26T00:39:46.9823347Z"
      },
      {
        "NewName": "FeedbackPanel (Container).SuccessIcon",
        "OldName": "FeedbackPanel (Container).ErrorIcon",
        "ElementType": "Components",
        "EventType": 7,
        "TimestampUtc": "2025-09-26T00:40:06.492281Z"
      },
      {
        "NewName": "FeedbackPanel (Container).ErrorIcon",
        "OldName": "FeedbackPanel (Container).SpriteInstance1",
        "ElementType": "Components",
        "EventType": 7,
        "TimestampUtc": "2025-09-26T00:40:19.2657053Z"
      },
      {
        "NewName": "MapEditor.SaveMapButton",
        "OldName": "MapEditor.ButtonConfirmInstance",
        "ElementType": "Screens",
        "EventType": 7,
        "TimestampUtc": "2025-09-26T00:42:13.402324Z"
      },
      {
        "NewName": "MapEditor.ContainerInstance",
        "OldName": null,
        "ElementType": "Screens",
        "EventType": 5,
        "TimestampUtc": "2025-09-30T02:43:49.8798206Z"
      },
      {
        "NewName": "MapEditor.LayerContainer",
        "OldName": "MapEditor.ContainerInstance",
        "ElementType": "Screens",
        "EventType": 7,
        "TimestampUtc": "2025-09-30T02:43:57.4025118Z"
      },
      {
        "NewName": "MapEditor.ButtonIconInstance",
        "OldName": null,
        "ElementType": "Screens",
        "EventType": 5,
        "TimestampUtc": "2025-09-30T02:45:46.7014679Z"
      },
      {
        "NewName": "MapEditor.ButtonIconInstance1",
        "OldName": null,
        "ElementType": "Screens",
        "EventType": 5,
        "TimestampUtc": "2025-09-30T02:45:56.1349587Z"
      },
      {
        "NewName": "MapEditor.UpLayer",
        "OldName": "MapEditor.ButtonIconInstance",
        "ElementType": "Screens",
        "EventType": 7,
        "TimestampUtc": "2025-09-30T02:46:02.7417612Z"
      },
      {
        "NewName": "MapEditor.LayerUpControl",
        "OldName": "MapEditor.UpLayer",
        "ElementType": "Screens",
        "EventType": 7,
        "TimestampUtc": "2025-09-30T02:46:09.0968258Z"
      },
      {
        "NewName": "MapEditor.LayerDownControl",
        "OldName": "MapEditor.ButtonIconInstance1",
        "ElementType": "Screens",
        "EventType": 7,
        "TimestampUtc": "2025-09-30T02:46:17.8436536Z"
      },
      {
        "NewName": "MapEditor.TextInstance",
        "OldName": null,
        "ElementType": "Screens",
        "EventType": 5,
        "TimestampUtc": "2025-09-30T02:46:28.0959199Z"
      },
      {
        "NewName": "MapEditor.TextLayer",
        "OldName": "MapEditor.TextInstance",
        "ElementType": "Screens",
        "EventType": 7,
        "TimestampUtc": "2025-09-30T02:46:34.649948Z"
      },
      {
        "NewName": "MapEditor.TextInstance",
        "OldName": null,
        "ElementType": "Screens",
        "EventType": 5,
        "TimestampUtc": "2025-10-04T17:49:42.8201178Z"
      },
      {
        "NewName": "MapEditor.TextBoxInstance",
        "OldName": null,
        "ElementType": "Screens",
        "EventType": 5,
        "TimestampUtc": "2025-10-04T17:51:08.2481061Z"
      },
      {
        "NewName": "MapEditor.TilesetNumText",
        "OldName": "MapEditor.TextBoxInstance",
        "ElementType": "Screens",
        "EventType": 7,
        "TimestampUtc": "2025-10-04T17:51:18.6261338Z"
      },
      {
        "NewName": "MapEditor.TilesetNumTextBox",
        "OldName": "MapEditor.TilesetNumText",
        "ElementType": "Screens",
        "EventType": 7,
        "TimestampUtc": "2025-10-04T17:51:25.6910761Z"
      },
      {
        "NewName": "MapEditor.TilesetNumText",
        "OldName": "MapEditor.TextInstance",
        "ElementType": "Screens",
        "EventType": 7,
        "TimestampUtc": "2025-10-04T17:51:32.3413656Z"
      },
      {
        "NewName": "MapEditor.ButtonStandardInstance",
        "OldName": null,
        "ElementType": "Screens",
        "EventType": 5,
        "TimestampUtc": "2025-10-04T17:59:49.2107635Z"
      },
      {
        "NewName": "MapEditor.ButtonStandardInstance1",
        "OldName": null,
        "ElementType": "Screens",
        "EventType": 5,
        "TimestampUtc": "2025-10-04T18:00:01.2040908Z"
      },
      {
        "NewName": "MapEditor.TilesetButton",
        "OldName": "MapEditor.ButtonStandardInstance",
        "ElementType": "Screens",
        "EventType": 7,
        "TimestampUtc": "2025-10-04T18:00:31.1453945Z"
      },
      {
        "NewName": "MapEditor.EventsButton",
        "OldName": "MapEditor.ButtonStandardInstance1",
        "ElementType": "Screens",
        "EventType": 7,
        "TimestampUtc": "2025-10-04T18:02:41.9787744Z"
      },
      {
        "NewName": "MapEditor.ContainerInstance",
        "OldName": null,
        "ElementType": "Screens",
        "EventType": 5,
        "TimestampUtc": "2025-10-04T18:04:11.5301077Z"
      },
      {
        "NewName": "MapEditor.EventsContainer",
        "OldName": "MapEditor.ContainerInstance",
        "ElementType": "Screens",
        "EventType": 7,
        "TimestampUtc": "2025-10-04T18:04:24.0988633Z"
      }
    ]
  }
}